{
  "routes": [
    {
      "method": "GET",
      "path": "/company-locations",
      "handler": "company-location.find",
      "config": {
        "policies": []
      }
    },
    {
      "method": "GET",
      "path": "/company-locations/count",
      "handler": "company-location.count",
      "config": {
        "policies": []
      }
    },
    {
      "method": "GET",
      "path": "/company-locations/:id",
      "handler": "company-location.findOne",
      "config": {
        "policies": []
      }
    },
    {
      "method": "POST",
      "path": "/company-locations",
      "handler": "company-location.create",
      "config": {
        "policies": []
      }
    },
    {
      "method": "PUT",
      "path": "/company-locations/:id",
      "handler": "company-location.update",
      "config": {
        "policies": []
      }
    },
    {
      "method": "DELETE",
      "path": "/company-locations/:id",
      "handler": "company-location.delete",
      "config": {
        "policies": []
      }
    }
  ]
}
